pocketsmith/__init__.py
pocketsmith/api/__init__.py
pocketsmith/api/accounts_api.py
pocketsmith/api/attachments_api.py
pocketsmith/api/budgeting_api.py
pocketsmith/api/categories_api.py
pocketsmith/api/category_rules_api.py
pocketsmith/api/data_feeds_accounts_api.py
pocketsmith/api/data_feeds_connections_api.py
pocketsmith/api/institutions_api.py
pocketsmith/api/transaction_accounts_api.py
pocketsmith/api/transactions_api.py
pocketsmith/api/users_api.py
pocketsmith/api_client.py
pocketsmith/apis/__init__.py
pocketsmith/configuration.py
pocketsmith/exceptions.py
pocketsmith/model/__init__.py
pocketsmith/model/account.py
pocketsmith/model/attachment.py
pocketsmith/model/attachment_content_type_meta.py
pocketsmith/model/attachment_variants.py
pocketsmith/model/budget_analysis.py
pocketsmith/model/budget_analysis_package.py
pocketsmith/model/category.py
pocketsmith/model/category_rule.py
pocketsmith/model/data_feeds_account.py
pocketsmith/model/data_feeds_account_balance.py
pocketsmith/model/data_feeds_connection.py
pocketsmith/model/data_feeds_connection_user.py
pocketsmith/model/error.py
pocketsmith/model/form.py
pocketsmith/model/form_fields.py
pocketsmith/model/form_options.py
pocketsmith/model/form_rows.py
pocketsmith/model/inline_object.py
pocketsmith/model/inline_object1.py
pocketsmith/model/inline_object10.py
pocketsmith/model/inline_object11.py
pocketsmith/model/inline_object12.py
pocketsmith/model/inline_object13.py
pocketsmith/model/inline_object14.py
pocketsmith/model/inline_object2.py
pocketsmith/model/inline_object3.py
pocketsmith/model/inline_object4.py
pocketsmith/model/inline_object5.py
pocketsmith/model/inline_object6.py
pocketsmith/model/inline_object7.py
pocketsmith/model/inline_object8.py
pocketsmith/model/inline_object9.py
pocketsmith/model/inline_response403.py
pocketsmith/model/institution.py
pocketsmith/model/period.py
pocketsmith/model/provider.py
pocketsmith/model/provider_provider_notices.py
pocketsmith/model/scenario.py
pocketsmith_api-2.1.1.dist-info/LICENSE
pocketsmith_api-2.1.1.dist-info/WHEEL
pocketsmith_api-2.1.1.dist-info/METADATA
pocketsmith_api-2.1.1.dist-info/RECORD
