Metadata-Version: 2.1
Name: pocketsmith-api
Version: 2.1.1
Summary: Pocketsmith API client
Home-page: https://github.com/theY4Kman/python-pocketsmith-api
License: MIT
Author: Zach "theY4Kman" Kanzler
Author-email: they4kman@gmail.com
Requires-Python: >=3.6
Classifier: Development Status :: 4 - Beta
Classifier: Intended Audience :: Developers
Classifier: Intended Audience :: Financial and Insurance Industry
Classifier: License :: OSI Approved :: MIT License
Classifier: Programming Language :: Python :: 3
Classifier: Programming Language :: Python :: 3.10
Classifier: Programming Language :: Python :: 3.6
Classifier: Programming Language :: Python :: 3.7
Classifier: Programming Language :: Python :: 3.8
Classifier: Programming Language :: Python :: 3.9
Classifier: Topic :: Internet :: WWW/HTTP
Requires-Dist: certifi
Requires-Dist: python-dateutil
Requires-Dist: six
Requires-Dist: urllib3[secure]
